{
  "code": "it",
  "name": "Italy",
  "region": "Europe",
  "iso2": "IT",
  "source_url": "https://unishka.substack.com/p/osint-of-italy",
  "note": "truncated to 35 of 77",
  "resources": [
    {"name": "Dati.gov.it", "url": "https://www.dati.gov.it", "category": "open-data", "note": "Italy's national open data portal", "keyless": true},
    {"name": "Registro delle Imprese", "url": "https://www.registroimprese.it", "category": "business-registry", "note": "main registry of all companies in Italy", "keyless": true},
    {"name": "Portale Antenati", "url": "https://antenati.cultura.gov.it/", "category": "archives", "note": "historic civil records: births, marriages, deaths", "keyless": true},
    {"name": "E-Justice Land Register", "url": "https://e-justice.europa.eu/topics/registers-business-insolvency-land/land-registers-eu-countries/it_en", "category": "land-property", "note": "EU land registry access", "keyless": true},
    {"name": "Codice Fiscale Online", "url": "https://www.codicefiscaleonline.com", "category": "finance-tax", "note": "Italian personal tax identification number", "keyless": true},
    {"name": "Web Whois NIC .it", "url": "https://web-whois.nic.it", "category": "telecom-infra", "note": "official .it domain WHOIS lookup", "keyless": true},
    {"name": "Supreme Court of Cassation", "url": "https://www.cortedicassazione.it", "category": "court-legal", "note": "Italy's highest court of appeal", "keyless": true},
    {"name": "Portale dei Servizi Telematici (PST)", "url": "https://servizipst.giustizia.it/PST/", "category": "court-legal", "note": "court registries and case files", "keyless": false},
    {"name": "Stolen/Lost Vehicle Search", "url": "https://crimnet.dcpc.interno.gov.it/crimnet/en/stolen_lost_vehicle_number_plate_researching", "category": "vehicle", "note": "official stolen vehicle database", "keyless": true},
    {"name": "Acquisti in Rete PA", "url": "https://www.acquistinretepa.it/opencms/opencms/", "category": "tenders", "note": "official e-procurement platform for public administration", "keyless": true},
    {"name": "White Pages - Italy", "url": "https://www.paginebianche.it/persone", "category": "people-search", "note": "national people directory", "keyless": true},
    {"name": "FlightRadar24", "url": "https://www.flightradar24.com", "category": "transport-tracking", "note": "live aircraft tracking", "keyless": true},
    {"name": "Vessel Finder", "url": "https://www.vesselfinder.com", "category": "transport-tracking", "note": "live vessel tracking", "keyless": true},
    {"name": "OpenCoesione", "url": "https://opencoesione.gov.it", "category": "open-data", "note": "EU cohesion policy project datasets", "keyless": true},
    {"name": "ANAC Open Data Portal", "url": "https://dati.anticorruzione.it", "category": "open-data", "note": "anti-corruption authority datasets", "keyless": true},
    {"name": "IstatData", "url": "https://esploradati.istat.it/databrowser/#/en", "category": "open-data", "note": "Italian National Institute of Statistics", "keyless": true},
    {"name": "OpenCorporates", "url": "https://opencorporates.com", "category": "business-registry", "note": "global corporate registry aggregator", "keyless": true},
    {"name": "OpenSanctions", "url": "https://www.opensanctions.org", "category": "sanctions-pep", "note": "contains 9,564 entities connected with Italy", "keyless": true},
    {"name": "Ministry of Justice", "url": "https://www.giustizia.it", "category": "government", "keyless": true},
    {"name": "Piattaforma Contratti Pubblici (ANAC)", "url": "https://www.anticorruzione.it/en/-/piattaforma-contratti-pubblici", "category": "tenders", "note": "national platform for public contracts", "keyless": true},
    {"name": "FlightAware", "url": "https://www.flightaware.com", "category": "transport-tracking", "note": "live flight tracker", "keyless": true},
    {"name": "Google Earth", "url": "https://www.google.it/intl/it/earth/index.html", "category": "maps-geo", "keyless": true},
    {"name": "Old Maps of Italy", "url": "https://www.oldmapsonline.org", "category": "maps-geo", "note": "historical maps collection", "keyless": true},
    {"name": "FamilySearch Historical Records", "url": "https://www.familysearch.org", "category": "archives", "note": "genealogical records and family history", "keyless": false},
    {"name": "Italian Trade Registry", "url": "https://traderegistry.it", "category": "business-registry", "keyless": true},
    {"name": "World Bank - Italy", "url": "https://data.worldbank.org/country/italy", "category": "open-data", "note": "World Bank development indicators", "keyless": true},
    {"name": "Europe's Most Wanted List", "url": "https://eumostwanted.eu", "category": "government", "note": "Eurojust wanted persons database", "keyless": true},
    {"name": "Italian Land Finder", "url": "https://www.landfinder.it", "category": "land-property", "keyless": true},
    {"name": "OCCRP Aleph", "url": "https://aleph.occrp.org", "category": "sanctions-pep", "note": "public records and leaks database", "keyless": true},
    {"name": "Public Vehicle Register (PRA) Searches", "url": "https://www.ponzi.com", "category": "vehicle", "note": "vehicle registration data", "keyless": false},
    {"name": "License Plates of Italy Lookup", "url": "https://platesmania.com", "category": "vehicle", "keyless": true},
    {"name": "TrueCaller", "url": "https://www.truecaller.com", "category": "phone", "note": "phone number lookup", "keyless": false},
    {"name": "OpenCivitas", "url": "https://www.opencivitas.it", "category": "open-data", "note": "comparative data on local governments", "keyless": true},
    {"name": "Lazio Regional Data", "url": "https://dati.lazio.it", "category": "open-data", "note": "regional government datasets", "keyless": true},
    {"name": "Italy's Most Wanted List", "url": "https://www.interno.gov.it", "category": "government", "note": "ministry interior wanted persons list", "keyless": true}
  ]
}
